agentsculptor/__init__.py
agentsculptor/main.py
agentsculptor/agent/__init__.py
agentsculptor/agent/loop.py
agentsculptor/agent/planner.py
agentsculptor/llm/__init__.py
agentsculptor/llm/client.py
agentsculptor/llm/prompts.py
agentsculptor/tools/__init__.py
agentsculptor/tools/dialog.py
agentsculptor/tools/prepare_context.py
agentsculptor/tools/refactor_code.py
agentsculptor/tools/registry.py
agentsculptor/tools/run_tests.py
agentsculptor/tools/update_imports.py
agentsculptor/utils/__init__.py
agentsculptor/utils/file_ops.py
agentsculptor/utils/logging.py
agentsculptor/utils/search.py
agentsculptor-0.1.13.dist-info/licenses/LICENSE
agentsculptor-0.1.13.dist-info/METADATA
agentsculptor-0.1.13.dist-info/WHEEL
agentsculptor-0.1.13.dist-info/entry_points.txt
agentsculptor-0.1.13.dist-info/top_level.txt
agentsculptor-0.1.13.dist-info/RECORD
