Metadata-Version: 2.4
Name: agentsculptor
Version: 0.1.13
Summary: AgentSculptor: Refactor, restructure & modernize codebases with natural language — powered by GPT-OSS and vLLM.
Home-page: https://github.com/Perpetue237/agentsculptor
Author: Perpetue237
Author-email: youremail@example.com
License: Apache-2.0
Project-URL: Bug Tracker, https://github.com/Perpetue237/agentsculptor/issues
Project-URL: Source, https://github.com/Perpetue237/agentsculptor
Project-URL: Demo, https://youtu.be/uI5hO-2xQ4k
Classifier: Programming Language :: Python :: 3
Classifier: Operating System :: OS Independent
Classifier: License :: OSI Approved :: Apache Software License
Requires-Python: >=3.12
License-File: LICENSE
Requires-Dist: black
Requires-Dist: pytest
Requires-Dist: colorlog
Requires-Dist: requests
Provides-Extra: dev
Requires-Dist: pytest; extra == "dev"
Dynamic: author
Dynamic: author-email
Dynamic: classifier
Dynamic: description
Dynamic: description-content-type
Dynamic: home-page
Dynamic: license
Dynamic: license-file
Dynamic: project-url
Dynamic: provides-extra
Dynamic: requires-dist
Dynamic: requires-python
Dynamic: summary
